rebecca.login-0.1-py3.3-nspkg.pth
rebecca/login/__init__.py
rebecca/login/tests/test_login.py
rebecca/login/tests/__init__.py
rebecca.login-0.1.dist-info/DESCRIPTION.rst
rebecca.login-0.1.dist-info/METADATA
rebecca.login-0.1.dist-info/namespace_packages.txt
rebecca.login-0.1.dist-info/pydist.json
rebecca.login-0.1.dist-info/RECORD
rebecca.login-0.1.dist-info/top_level.txt
rebecca.login-0.1.dist-info/WHEEL
