Metadata-Version: 2.0
Name: rebecca.login
Version: 0.1
Summary: UNKNOWN
Home-page: https://github.com/rebeccaframework/rebecca.login
Author: Atsushi Odagiri
Author-email: aodagx@gmail.com
License: MIT
Platform: UNKNOWN
Classifier: Programming Language :: Python
Classifier: Programming Language :: Python :: 2.7
Classifier: Programming Language :: Python :: 3
Classifier: Programming Language :: Python :: 3.3
Classifier: Framework :: Pyramid
Requires-Dist: pyramid
Requires-Dist: rebecca.repository
Requires-Dist: setuptools (>=0.7)
Provides-Extra: testing
Requires-Dist: testfixtures; extra == 'testing'
